oopt_gnpy_libyang.cpython-310-x86_64-linux-gnu.so
oopt_gnpy_libyang-0.0.14.dist-info/WHEEL
oopt_gnpy_libyang-0.0.14.dist-info/top_level.txt
oopt_gnpy_libyang-0.0.14.dist-info/LICENSE
oopt_gnpy_libyang-0.0.14.dist-info/RECORD
oopt_gnpy_libyang-0.0.14.dist-info/METADATA
oopt_gnpy_libyang.libs/libyang-cpp-ecbf2ba8.so
oopt_gnpy_libyang.libs/libyang-e953a79e.so.2.47.2
oopt_gnpy_libyang.libs/libpcre2-8-9a491624.so.0.11.0
