Metadata-Version: 2.1
Name: oopt-gnpy-libyang
Version: 0.0.14
Summary: Opinionated Python bindings for the libyang library
Home-page: https://github.com/Telecominfraproject/oopt-gnpy-libyang
Download-URL: https://pypi.org/project/oopt-gnpy-libyang/
Author: Telecom Infra Project
Author-email: jan.kundrat@telecominfraproject.com
License: BSD-3-Clause
Classifier: Intended Audience :: Developers
Classifier: Intended Audience :: Science/Research
Classifier: Intended Audience :: Telecommunications Industry
Classifier: License :: OSI Approved :: BSD License
Classifier: Programming Language :: Python
Classifier: Programming Language :: Python :: 3 :: Only
Classifier: Programming Language :: Python :: 3.8
Classifier: Programming Language :: Python :: 3.9
Classifier: Programming Language :: Python :: 3.10
Classifier: Programming Language :: Python :: 3.11
Classifier: Programming Language :: Python :: 3.12
Classifier: Programming Language :: Python :: Implementation :: CPython
Classifier: Topic :: System :: Networking
Requires-Python: >=3.8
License-File: LICENSE
Provides-Extra: test
Requires-Dist: pytest>=6.0; extra == "test"
